{"type": "FeatureCollection", "id": "http://wikidata.org/entity/Q52035", "name": "Q52035", "features": [{"type": "Feature", "id": "http://fuzzy-sl.squirrel.link/data/site_3001", "name": "San Giorgio Ionico 1949", "dateprops": [], "properties": {"http://archaeoinformatics.link/ontology#certaintyDesc": ["Wo befand sich der Grundbesitz des E. De Finis?"], "http://archaeoinformatics.link/ontology#certaintyLevel": ["http://archaeoinformatics.link/ontology#medium"], "http://archaeoinformatics.link/ontology#hasReference": ["F. G. Lo Porto (1990)", "A. Siciliano (2001)"], "http://archaeoinformatics.link/ontology#partOf": ["http://archaeoinformatics.link/ontology#CrotonProject"], "http://archaeoinformatics.link/ontology#siteType": ["http://archaeoinformatics.link/ontology#ArchaeologicalSite"], "http://archaeoinformatics.link/ontology#spatialCloseMatch": ["http://wikidata.org/entity/Q52035", "http://openstreetmap.org/node/68530185"], "http://archaeoinformatics.link/ontology#spatialType": ["http://archaeoinformatics.link/ontology#InhabitedPlace"], "http://purl.org/dc/terms/creator": ["https://orcid.org/0000-0002-3246-3531", "https://orcid.org/0000-0003-1100-6494"], "http://purl.org/dc/terms/license": ["https://creativecommons.org/licenses/by/4.0/"], "http://purl.org/dc/terms/rightsHolder": ["https://orcid.org/0000-0002-3246-3531", "https://orcid.org/0000-0003-1100-6494"], "http://www.opengis.net/ont/geosparql#hasGeometry": ["http://fuzzy-sl.squirrel.link/data/site_3001_geom"], "http://www.w3.org/1999/02/22-rdf-syntax-ns#type": ["http://archaeoinformatics.link/ontology#Site", "http://www.w3.org/ns/prov#Entity", "https://pleiades.stoa.org/places/vocab#Place"], "http://www.w3.org/2000/01/rdf-schema#comment": ["San Giorgio Ionico (bei Tarent), auf dem Grundbesitz von `E. De Finis`."], "http://www.w3.org/2000/01/rdf-schema#label": ["San Giorgio Ionico 1949"], "http://www.w3.org/2004/02/skos/core#prefLabel": ["San Giorgio Ionico 1949"], "http://www.w3.org/2004/02/skos/core#scopeNote": ["San Giorgio Ionico (bei Tarent), auf dem Grundbesitz von `E. De Finis`."], "http://www.w3.org/ns/prov#wasAttributedTo": ["http://orcid.org/0000-0003-1100-6494", "https://github.com/Research-Squirrel-Engineers/croton-geo/blob/main/py/croton.py"], "http://www.w3.org/ns/prov#wasDerivedFrom": ["https://github.com/Research-Squirrel-Engineers/croton-geo"], "http://www.w3.org/ns/prov#wasGeneratedBy": ["http://fuzzy-sl.squirrel.link/data/site_3001_activity", "http://fuzzy-sl.squirrel.link/data/site_3001_pyscript"]}, "geometry": {"type": "Point", "coordinates": [17.3787, 40.4579], "crs": "4326"}}], "numberMatched": 1, "numberReturned": 1, "bbox": [17.3787, 40.4579, 17.3787, 40.4579], "crs": "http://www.opengis.net/def/crs/EPSG/0/4326"}