{"type": "FeatureCollection", "id": "http://fuzzy-sl.squirrel.link/data/Site_collection", "name": "Site Instances Collection", "features": [{"type": "Feature", "id": "http://fuzzy-sl.squirrel.link/data/site_1002", "name": "Paestum (anc. Poseidonia), Lucania (fsld:site_1002)", "dateprops": [], "properties": {}, "geometry": {"type": "Point", "coordinates": [15.00731, 40.4223], "crs": "4326"}}, {"type": "Feature", "id": "http://fuzzy-sl.squirrel.link/data/site_1001", "name": "Taranto, Via Oberdan (fsld:site_1001)", "dateprops": [], "properties": {}, "geometry": {"type": "Point", "coordinates": [17.24707, 40.46438], "crs": "4326"}}], "numberMatched": 2, "numberReturned": 2, "bbox": [15.00731, 40.4223, 17.24707, 40.46438], "crs": "http://www.opengis.net/def/crs/EPSG/0/4326"}